greenotyper-0.7.0.data/data/icon.png
greenotyper-0.7.0.data/scripts/greenotyper
greenotyperAPI/GREENOTYPER.py
greenotyperAPI/__init__.py
greenotyperAPI/GUI/PipelinePlanner.py
greenotyperAPI/GUI/PipelineRunner.py
greenotyperAPI/GUI/__init__.py
greenotyperAPI/GUI/qrangeslider.py
greenotyper-0.7.0.dist-info/LICENSE
greenotyper-0.7.0.dist-info/METADATA
greenotyper-0.7.0.dist-info/WHEEL
greenotyper-0.7.0.dist-info/top_level.txt
greenotyper-0.7.0.dist-info/RECORD
