Metadata-Version: 2.1
Name: greenotyper
Version: 0.7.0
Summary: Plant image-based phenotyping pipeline
Home-page: https://github.com/MarniTausen/Greenotyper
Author: Marni Tausen
Author-email: marni.tausen@gmail.com
License: UNKNOWN
Keywords: phenotyping detection
Platform: UNKNOWN
Classifier: Programming Language :: Python :: 3.6
Classifier: Programming Language :: Python :: 3.7
Classifier: License :: OSI Approved :: MIT License
Classifier: Operating System :: OS Independent
Classifier: Development Status :: 4 - Beta
Requires-Python: ~=3.6
Requires-Dist: tensorflow (>=2)
Requires-Dist: PyQt5 (>=5.9)
Requires-Dist: numpy (>=1.15)
Requires-Dist: scikit-image (>=0.14)
Requires-Dist: pillow (>=5.2)
Requires-Dist: tqdm (>=4.40)
